Metadata-Version: 2.4
Name: adafruit-circuitpython-jd79667
Version: 1.0.1
Summary: CircuitPython library for the JD79667 e-paper driver IC
Author-email: Adafruit Industries <circuitpython@adafruit.com>
License: MIT
Project-URL: Homepage, https://github.com/adafruit/Adafruit_CircuitPython_JD79667
Keywords: adafruit,blinka,circuitpython,micropython,jd79667,epd,epaper
Classifier: Intended Audience :: Developers
Classifier: Topic :: Software Development :: Libraries
Classifier: Topic :: Software Development :: Embedded Systems
Classifier: Topic :: System :: Hardware
Classifier: License :: OSI Approved :: MIT License
Classifier: Programming Language :: Python :: 3
License-File: LICENSE
Requires-Dist: Adafruit-Blinka
Provides-Extra: optional
Dynamic: license-file
